cmdprogress/__init__.py
cmdprogress/bar.py
cmdprogress/core.py
cmdprogress/multi.py
cmdprogress-1.2.dist-info/LICENSE
cmdprogress-1.2.dist-info/METADATA
cmdprogress-1.2.dist-info/WHEEL
cmdprogress-1.2.dist-info/top_level.txt
cmdprogress-1.2.dist-info/RECORD
