Metadata-Version: 2.1
Name: cmdprogress
Version: 1.2
Summary: Command Line Progress Bars
Home-page: https://github.com/luciancooper/cmdprogress
Author: Lucian Cooper
License: MIT
Keywords: progress bar utility
Platform: UNKNOWN
Classifier: Environment :: Console
Classifier: Intended Audience :: Developers
Classifier: License :: OSI Approved :: MIT License
Classifier: Programming Language :: Python
Classifier: Programming Language :: Python :: 3.6
Classifier: Operating System :: MacOS
Classifier: Operating System :: Microsoft :: Windows
Classifier: Operating System :: POSIX :: Linux
Classifier: Topic :: Terminals
Classifier: Topic :: Utilities
Requires-Dist: colorama ; platform_system == "Windows"
